vplot/__init__.py
vplot/auto_plot.py
vplot/colors.py
vplot/command_line.py
vplot/figure.py
vplot/vplot_version.py
vplot/style/__init__.py
vplot/style/vplot.mplstyle
vplot-1.0.5.dist-info/LICENSE
vplot-1.0.5.dist-info/METADATA
vplot-1.0.5.dist-info/WHEEL
vplot-1.0.5.dist-info/entry_points.txt
vplot-1.0.5.dist-info/top_level.txt
vplot-1.0.5.dist-info/RECORD
