Metadata-Version: 2.1
Name: vplot
Version: 1.0.5
Summary: plotting tools for vplanet
Home-page: https://github.com/VirtualPlanetaryLaboratory/vplot/
Author: Rodrigo Luger
Author-email: rodluger@gmail.edu
License: MIT
License-File: LICENSE
Requires-Dist: setuptools-scm
Requires-Dist: numpy >=1.19.2
Requires-Dist: matplotlib >=3.3.4
Requires-Dist: astropy >=4.1
Requires-Dist: vplanet >=2.0.0
